ctfdumper/__init__.py
ctfdumper/ctfdumper.py
ctfdumper/run.py
ctfdumper-1.0.1.dist-info/LICENSE
ctfdumper-1.0.1.dist-info/METADATA
ctfdumper-1.0.1.dist-info/WHEEL
ctfdumper-1.0.1.dist-info/entry_points.txt
ctfdumper-1.0.1.dist-info/top_level.txt
ctfdumper-1.0.1.dist-info/RECORD
